scrapio/__init__.py
scrapio/crawlers/__init__.py
scrapio/crawlers/base_crawler.py
scrapio/parsing/__init__.py
scrapio/parsing/links.py
scrapio/requests/__init__.py
scrapio/requests/client.py
scrapio/requests/client_configuration.py
scrapio/requests/default_client.py
scrapio/requests/response.py
scrapio/retries/__init__.py
scrapio/retries/retry.py
scrapio/structures/__init__.py
scrapio/structures/filtering.py
scrapio/structures/proxies.py
scrapio/structures/queues.py
scrapio/structures/rate_limiter.py
scrapio/url_set/__init__.py
scrapio/url_set/abstract_set.py
scrapio/url_set/set_container.py
scrapio/url_set/trie_container.py
scrapio/utils/__init__.py
scrapio/utils/helpers.py
scrapio/utils/urls.py
scrapio-0.2.0.dist-info/LICENSE
scrapio-0.2.0.dist-info/METADATA
scrapio-0.2.0.dist-info/WHEEL
scrapio-0.2.0.dist-info/top_level.txt
scrapio-0.2.0.dist-info/RECORD
